barikoiapis/__init__.py
barikoiapis/api/__init__.py
barikoiapis/api/v2_0/__init__.py
barikoiapis/api/v2_0/autocomplete.py
barikoiapis/api/v2_0/calculate_route.py
barikoiapis/api/v2_0/check_nearby.py
barikoiapis/api/v2_0/geocode.py
barikoiapis/api/v2_0/nearby.py
barikoiapis/api/v2_0/optimize_route.py
barikoiapis/api/v2_0/place_details.py
barikoiapis/api/v2_0/reverse_geocode.py
barikoiapis/api/v2_0/route_overview.py
barikoiapis/api/v2_0/search_place.py
barikoiapis/api/v2_0/snap_to_road.py
barikoiapis/client.py
barikoiapis/errors.py
barikoiapis/models/__init__.py
barikoiapis/models/api_limit_exceeded.py
barikoiapis/models/autocomplete_success.py
barikoiapis/models/autocomplete_success_places_item.py
barikoiapis/models/calculate_route_body.py
barikoiapis/models/calculate_route_body_data.py
barikoiapis/models/calculate_route_body_data_destination.py
barikoiapis/models/calculate_route_body_data_start.py
barikoiapis/models/calculate_route_profile.py
barikoiapis/models/calculate_route_type.py
barikoiapis/models/check_nearby_success.py
barikoiapis/models/check_nearby_success_data.py
barikoiapis/models/geocode_body.py
barikoiapis/models/geocode_body_bangla.py
barikoiapis/models/geocode_body_district.py
barikoiapis/models/geocode_body_thana.py
barikoiapis/models/geocode_success.py
barikoiapis/models/geocode_success_address_status.py
barikoiapis/models/geocode_success_geocoded_address.py
barikoiapis/models/missing_parameter.py
barikoiapis/models/nearby_success.py
barikoiapis/models/nearby_success_places_item.py
barikoiapis/models/no_registered_key.py
barikoiapis/models/payment_exception.py
barikoiapis/models/place_details_success.py
barikoiapis/models/place_details_success_place.py
barikoiapis/models/reverse_geocode_success.py
barikoiapis/models/reverse_geocode_success_place.py
barikoiapis/models/reverse_geocode_success_place_address_components_type_0.py
barikoiapis/models/reverse_geocode_success_place_area_components_type_0.py
barikoiapis/models/route_optimization_body.py
barikoiapis-2.0.2.dist-info/METADATA
barikoiapis-2.0.2.dist-info/WHEEL
barikoiapis-2.0.2.dist-info/licenses/LICENSE
barikoiapis-2.0.2.dist-info/RECORD
