Metadata-Version: 2.4
Name: barikoiapis
Version: 2.0.2
Summary: Official Python SDK for Barikoi Location Services - search, geocoding, routing, and more
License: MIT
License-File: LICENSE
Keywords: barikoi,location,geocoding,maps,routing,api
Author: Barikoi hello@barikoi.com
Requires-Python: >=3.10,<4.0
Classifier: Development Status :: 4 - Beta
Classifier: Intended Audience :: Developers
Classifier: License :: OSI Approved :: MIT License
Classifier: Programming Language :: Python :: 3
Classifier: Programming Language :: Python :: 3.10
Classifier: Programming Language :: Python :: 3.11
Classifier: Programming Language :: Python :: 3.12
Classifier: Programming Language :: Python :: 3.13
Classifier: Programming Language :: Python :: 3.14
Classifier: Topic :: Scientific/Engineering :: GIS
Classifier: Topic :: Software Development :: Libraries :: Python Modules
Requires-Dist: attrs (>=22.2.0)
Requires-Dist: httpx (>=0.23.0,<0.29.0)
Requires-Dist: python-dateutil (>=2.8.0,<3.0.0)
Project-URL: Bug Tracker, https://github.com/barikoi/python-client/issues
Project-URL: Documentation, https://docs.barikoi.com
Project-URL: Homepage, https://barikoi.com
Project-URL: Repository, https://github.com/barikoi/python-client
Project-URL: Support, https://barikoi.com/
